pizazz/__init__.py
pizazz/pizazz.py
pizazz-1.3.5.dist-info/AUTHORS.md
pizazz-1.3.5.dist-info/LICENSE
pizazz-1.3.5.dist-info/METADATA
pizazz-1.3.5.dist-info/WHEEL
pizazz-1.3.5.dist-info/entry_points.txt
pizazz-1.3.5.dist-info/top_level.txt
pizazz-1.3.5.dist-info/RECORD
